pgtg_widgets/__init__.py
pgtg_widgets/catchers.py
pgtg_widgets/example_demonstration.py
pgtg_widgets/widgets.py
pgtg_widgets-0.0.6.dist-info/LICENSE
pgtg_widgets-0.0.6.dist-info/METADATA
pgtg_widgets-0.0.6.dist-info/WHEEL
pgtg_widgets-0.0.6.dist-info/top_level.txt
pgtg_widgets-0.0.6.dist-info/RECORD
