Metadata-Version: 2.1
Name: pgtg-widgets
Version: 0.0.6
Summary: widgets for pygame
Author-email: Tea-Guardian <grammarline@yandex.ru>
Project-URL: Homepage, https://github.com/TeaGuardian/pgtg_widgets
Project-URL: Bug Tracker, https://github.com/TeaGuardian/pgtg_widgets/issues
Classifier: Programming Language :: Python :: 3
Classifier: License :: OSI Approved :: Apache Software License
Classifier: Operating System :: OS Independent
Requires-Python: >=3.7
License-File: LICENSE
